pyrolint/main.py
pyrolint/test_rules.py
pyrolint-0.1.0.dist-info/WHEEL
pyrolint-0.1.0.dist-info/METADATA
pyrolint-0.1.0.dist-info/RECORD
