Metadata-Version: 2.1
Name: pyrolint
Version: 0.1.0
Summary: 
Home-page: UNKNOWN
License: UNKNOWN
Author: Steve Dignam
Author-email: steve@dignam.xyz
Requires-Python: >=3.7,<4.0
Classifier: Programming Language :: Python :: 3
Classifier: Programming Language :: Python :: 3.7
Requires-Dist: libcst (>=0.3.7,<0.4.0)
